{"site_detail_url":"http://www.giantbomb.com/artrageous/61-100/","characters":[],"videos":[],"deck":"An edutainment game which aims to teach players about art.","image":{"icon_url":"http://media.giantbomb.com/uploads/10/103221/1803050-ar_icon.jpg","medium_url":"http://media.giantbomb.com/uploads/10/103221/1803050-ar_small.jpg","tiny_url":"http://media.giantbomb.com/uploads/10/103221/1803050-ar_tiny.jpg","small_url":"http://media.giantbomb.com/uploads/10/103221/1803050-ar_small.jpg","thumb_url":"http://media.giantbomb.com/uploads/10/103221/1803050-ar_thumb.jpg","screen_url":"http://media.giantbomb.com/uploads/10/103221/1803050-ar_screen.jpg","super_url":"http://media.giantbomb.com/uploads/10/103221/1803050-ar_super.jpg"},"locations":[],"themes":[],"platforms":[{"api_detail_url":"http://api.giantbomb.com/platform/17/","site_detail_url":"http://www.giantbomb.com/mac/60-17/","id":17,"name":"Mac"},{"api_detail_url":"http://api.giantbomb.com/platform/94/","site_detail_url":"http://www.giantbomb.com/pc/60-94/","id":94,"name":"PC"}],"expected_release_month":null,"similar_games":[],"images":[],"id":100,"aliases":"","first_appearance_locations":[],"genres":[{"api_detail_url":"http://api.giantbomb.com/genre/8/","site_detail_url":"http://www.giantbomb.com/games/?sort=release_date&filter_type=genre&filter_value=8","id":8,"name":"Educational"}],"people":[],"original_release_date":null,"first_appearance_characters":[],"developers":[{"api_detail_url":"http://api.giantbomb.com/company/179/","site_detail_url":"http://www.giantbomb.com/superstudio-ltd/65-179/","id":179,"name":"SuperStudio Ltd."}],"first_appearance_objects":[],"expected_release_year":null,"publishers":[{"api_detail_url":"http://api.giantbomb.com/company/178/","site_detail_url":"http://www.giantbomb.com/future-vision-multimedia/65-178/","id":178,"name":"Future Vision Multimedia"}],"date_last_updated":"2012-09-15 18:14:39","expected_release_quarter":null,"first_appearance_people":[],"description":"<p>.</p>","releases":[],"franchises":[],"api_detail_url":"http://api.giantbomb.com/game/100/","number_of_user_reviews":0,"objects":[],"original_game_rating":null,"date_added":"2008-04-01 01:33:09","first_appearance_concepts":[],"name":"ArtRageous!","killed_characters":[],"reviews":[],"concepts":[]}